{"assets/fonts/AirbnbCerealBlack.ttf":["assets/fonts/AirbnbCerealBlack.ttf"],"assets/fonts/AirbnbCerealBold.ttf":["assets/fonts/AirbnbCerealBold.ttf"],"assets/fonts/AirbnbCerealBook.ttf":["assets/fonts/AirbnbCerealBook.ttf"],"assets/fonts/AirbnbCerealExtraBold.ttf":["assets/fonts/AirbnbCerealExtraBold.ttf"],"assets/fonts/AirbnbCerealLight.ttf":["assets/fonts/AirbnbCerealLight.ttf"],"assets/fonts/AirbnbCerealMedium.ttf":["assets/fonts/AirbnbCerealMedium.ttf"],"packages/cupertino_icons/assets/CupertinoIcons.ttf":["packages/cupertino_icons/assets/CupertinoIcons.ttf"]}